{
  "_note": "Generated by scripts/refresh_prices.py. coupang = curated snapshot (headed session); iherb = T3 iherb_products.json. Do not hand-edit; rerun the script.",
  "updated": "2026-07-20T11:28:57+09:00",
  "items": {
    "arginine": {
      "coupang": {
        "price": 20220,
        "url": "https://link.coupang.com/a/fwPMOvU4Mm",
        "product": "나우푸드 더블 스트랭스 L-아르기닌 1000mg"
      },
      "iherb": {
        "price": 19155,
        "url": "https://kr.iherb.com/pr/now-foods-l-arginine-1-000-mg-120-tablets/411?rcode=NEE1183",
        "product": "NOW Foods, L-Arginine, 1000mg, 120정"
      }
    },
    "astaxanthin": {
      "coupang": {
        "price": 35990,
        "url": "https://link.coupang.com/a/fwPOL8I8gm",
        "product": "스포츠리서치 트리플 스트렝스 아스타잔틴 12mg"
      }
    },
    "cla": {
      "coupang": {
        "price": 40720,
        "url": "https://link.coupang.com/a/fwPNNlJi9I",
        "product": "스포츠리서치 맥스 포텐시 CLA 1250mg"
      },
      "iherb": {
        "price": 42557,
        "url": "https://kr.iherb.com/pr/sports-research-cla-1250-max-strength-1-250-mg-180-softgels/72036?rcode=NEE1183",
        "product": "Sports Research, CLA 1250, 180 소프트젤"
      }
    },
    "eveningprimrose": {
      "coupang": {
        "price": 35450,
        "url": "https://link.coupang.com/a/fwPYAUC924",
        "product": "스완슨 이브닝 프림로즈 오일 소프트젤 250정"
      },
      "iherb": {
        "price": 25538,
        "url": "https://kr.iherb.com/pr/now-foods-super-primrose-1-300-mg-120-softgels/851?rcode=NEE1183",
        "product": "NOW Foods, Super Primrose 1300mg, 120 소프트젤"
      }
    },
    "glucomannan": {
      "coupang": {
        "price": 22860,
        "url": "https://link.coupang.com/a/fwPSHDa75w",
        "product": "나우푸드 글루코만난 575mg 캡슐"
      },
      "iherb": {
        "price": 22923,
        "url": "https://kr.iherb.com/pr/now-foods-glucomannan-575-mg-180-veg-capsules/6673?rcode=NEE1183",
        "product": "NOW Foods, Glucomannan 575mg, 180 베지캡슐"
      }
    },
    "maca": {
      "coupang": {
        "price": 29000,
        "url": "https://link.coupang.com/a/fwP63v5fEa",
        "product": "나우푸드 마카 무가공 750mg 베지캡슐"
      }
    },
    "phosphatidylserine": {
      "coupang": {
        "price": 44590,
        "url": "https://link.coupang.com/a/fwQkOi9P64",
        "product": "나우푸드 포스파티딜 세린 100mg 베지 캡슐"
      }
    },
    "soyisoflavone": {
      "coupang": {
        "price": 35880,
        "url": "https://link.coupang.com/a/fwNLzNW776",
        "product": "파이토젠 로얄캐네디언 대두 이소플라본 리그난"
      }
    },
    "tartcherry": {
      "coupang": {
        "price": 46900,
        "url": "https://link.coupang.com/a/fwPXBYmzwO",
        "product": "마이라이프 내추럴스 몽모랑시 타트체리"
      }
    },
    "vitd": {
      "iherb": {
        "price": 22641,
        "url": "https://kr.iherb.com/pr/california-gold-nutrition-vitamin-d3-125-mcg-5-000-iu-360-fish-gelatin-softgels/70317?rcode=NEE1183",
        "product": "California Gold Nutrition, D3 5000IU, 360 소프트젤"
      }
    },
    "zinc": {
      "iherb": {
        "price": 15312,
        "url": "https://kr.iherb.com/pr/now-foods-zinc-picolinate-50-mg-120-veg-capsules/878?rcode=NEE1183",
        "product": "NOW Foods, 피콜린산 아연 50mg, 120 베지캡슐"
      }
    }
  }
}
